ztrack/__init__.py
ztrack/__main__.py
ztrack/_annotate.py
ztrack/_create_config.py
ztrack/_run_gui.py
ztrack/_run_tracking.py
ztrack/_settings.py
ztrack/_view_results.py
ztrack/cli.py
ztrack/gui/__init__.py
ztrack/gui/_control_widget.py
ztrack/gui/_main_window.py
ztrack/gui/_tracking_plot_widget.py
ztrack/gui/annotator.py
ztrack/gui/behavior_analyzer/__init__.py
ztrack/gui/behavior_analyzer/behavior_analyzer.py
ztrack/gui/behavior_analyzer/control_widget.py
ztrack/gui/behavior_analyzer/multirow.py
ztrack/gui/behavior_analyzer/plot_widget.py
ztrack/gui/create_config.py
ztrack/gui/img/logo.svg
ztrack/gui/menu_widget.py
ztrack/gui/tracking_viewer.py
ztrack/gui/utils/__init__.py
ztrack/gui/utils/file.py
ztrack/gui/utils/frame_bar.py
ztrack/gui/utils/launch.py
ztrack/gui/utils/variable_widgets.py
ztrack/metadata.py
ztrack/tracking/__init__.py
ztrack/tracking/eye/__init__.py
ztrack/tracking/eye/adaptive_threshold.py
ztrack/tracking/eye/binary.py
ztrack/tracking/eye/eye_tracker.py
ztrack/tracking/eye/eyes_only.py
ztrack/tracking/eye/multi_threshold.py
ztrack/tracking/free/__init__.py
ztrack/tracking/free/base.py
ztrack/tracking/free/contour.py
ztrack/tracking/free/sequential.py
ztrack/tracking/mixins/__init__.py
ztrack/tracking/mixins/background.py
ztrack/tracking/paramecia/__init__.py
ztrack/tracking/paramecia/paramecia.py
ztrack/tracking/params.py
ztrack/tracking/tail/__init__.py
ztrack/tracking/tail/com.py
ztrack/tracking/tail/gradient.py
ztrack/tracking/tail/gradient2.py
ztrack/tracking/tail/sequential.py
ztrack/tracking/tail/sequential2.py
ztrack/tracking/tail/sequential_sato.py
ztrack/tracking/tail/tail_tracker.py
ztrack/tracking/tracker.py
ztrack/utils/__init__.py
ztrack/utils/cv.py
ztrack/utils/exception.py
ztrack/utils/file.py
ztrack/utils/geometry.py
ztrack/utils/math.py
ztrack/utils/shape.py
ztrack/utils/typing.py
ztrack/utils/variable.py
ztrack-1.2.0.dist-info/entry_points.txt
ztrack-1.2.0.dist-info/METADATA
ztrack-1.2.0.dist-info/WHEEL
ztrack-1.2.0.dist-info/RECORD
